squids/__init__.py
squids/__main__.py
squids/cli.py
squids/consumer.py
squids/core.py
squids/serde.py
squids-0.1.0a2.dist-info/LICENSE
squids-0.1.0a2.dist-info/METADATA
squids-0.1.0a2.dist-info/WHEEL
squids-0.1.0a2.dist-info/RECORD
